yr_weather/__init__.py
yr_weather/client.py
yr_weather/geosatellite.py
yr_weather/locationforecast.py
yr_weather/py.typed
yr_weather/radar.py
yr_weather/sunrise.py
yr_weather/textforecast.py
yr_weather/api_types/__init__.py
yr_weather/api_types/geosatellite.py
yr_weather/api_types/locationforecast.py
yr_weather/api_types/radar.py
yr_weather/api_types/sunrise.py
yr_weather/api_types/textforecast.py
yr_weather/data/locationforecast.py
yr_weather/data/radar.py
yr_weather/data/sunrise.py
yr_weather/data/textforecast.py
yr_weather-0.4.0.dist-info/LICENSE
yr_weather-0.4.0.dist-info/METADATA
yr_weather-0.4.0.dist-info/WHEEL
yr_weather-0.4.0.dist-info/top_level.txt
yr_weather-0.4.0.dist-info/RECORD
