Metadata-Version: 2.1
Name: yr-weather
Version: 0.4.0
Summary: Retrieve weather data from Norwegian Meteorological Institute's APIs easily.
Author: ZeroWave022
Project-URL: Homepage, https://github.com/ZeroWave022/yr-weather
Project-URL: Bug Tracker, https://github.com/ZeroWave022/yr-weather/issues
Classifier: Development Status :: 4 - Beta
Classifier: Programming Language :: Python :: 3.8
Classifier: Programming Language :: Python :: 3.9
Classifier: Programming Language :: Python :: 3.10
Classifier: Programming Language :: Python :: 3.11
Classifier: License :: OSI Approved :: Apache Software License
Classifier: Operating System :: OS Independent
Classifier: Natural Language :: English
Classifier: Topic :: Internet
Classifier: Intended Audience :: Developers
Classifier: Typing :: Typed
Requires-Python: >=3.8
License-File: LICENSE
Requires-Dist: requests
Requires-Dist: requests-cache
Requires-Dist: pytz
Requires-Dist: xmltodict
